jwst_proposal_helper/__init__.py
jwst_proposal_helper/append_spc.py
jwst_proposal_helper/prepare_KN_nebular_spc.py
jwst_proposal_helper/read_spc_at2017gfo.py
jwst_proposal_helper/read_spc_even2020.py
jwst_proposal_helper/rescale_spc.py
jwst_proposal_helper-1.2.1.dist-info/LICENSE
jwst_proposal_helper-1.2.1.dist-info/METADATA
jwst_proposal_helper-1.2.1.dist-info/WHEEL
jwst_proposal_helper-1.2.1.dist-info/top_level.txt
jwst_proposal_helper-1.2.1.dist-info/RECORD
