Metadata-Version: 2.1
Name: jwst-proposal-helper
Version: 1.2.1
Summary: UNKNOWN
Home-page: https://github.com/bkornpob/jwst_proposal_helper.git
Author: Kornpob Bhirombhakdi
Author-email: kbhirombhakdi@stsci.edu
License: UNKNOWN
Platform: UNKNOWN
Classifier: Programming Language :: Python :: 3
Classifier: License :: OSI Approved :: MIT License
Classifier: Operating System :: OS Independent
Requires-Python: >=3.
